setup.py
django_nullmailer.egg-info/PKG-INFO
django_nullmailer.egg-info/SOURCES.txt
django_nullmailer.egg-info/dependency_links.txt
django_nullmailer.egg-info/top_level.txt
nullmailer/__init__.py
nullmailer/backend.py