Metadata-Version: 1.0
Name: django-nullmailer
Version: 0.1
Summary: A django EMAIL_BACKEND for enqueuing mail in nullmailer spool system.
Home-page: https://github.com/20tab/django-nullmailer
Author: 20Tab S.r.l.
Author-email: info@20tab.com
License: UNKNOWN
Platform: UNKNOWN
